{
  "headers": [
    { "accessorKey": "notificationId", "header": "Notification ID" },
    { "accessorKey": "companyCode", "header": "Company Code" },
    { "accessorKey": "branchCode", "header": "Branch Code" },
    { "accessorKey": "departmentCode", "header": "Department Code" },
    { "accessorKey": "customer", "header": "Customer" },
    { "accessorKey": "orderType", "header": "Order Type" },
    { "accessorKey": "service", "header": "Service" },
    { "accessorKey": "product", "header": "Product" },
    { "accessorKey": "incoTerms", "header": "Inco Terms" },
    { "accessorKey": "fromCountry", "header": "From Country" },
    { "accessorKey": "toCountry", "header": "To Country" }
  ],
  "rows": [
    {
      "notificationId": "N001",
      "companyCode": "CMP01",
      "branchCode": "BR01",
      "departmentCode": "D001",
      "customer": "Customer A",
      "orderType": "Standard",
      "service": "Express",
      "product": "Electronics",
      "incoTerms": "FOB",
      "fromCountry": "India",
      "toCountry": "Germany"
    },
    {
      "notificationId": "N002",
      "companyCode": "CMP02",
      "branchCode": "BR02",
      "departmentCode": "D002",
      "customer": "Customer B",
      "orderType": "Premium",
      "service": "Regular",
      "product": "Furniture",
      "incoTerms": "CIF",
      "fromCountry": "USA",
      "toCountry": "India"
    }
  ]
}
